markitdown_mcp_server/__init__.py
markitdown_mcp_server/server.py
markitdown_mcp_server-0.1.11.dist-info/METADATA
markitdown_mcp_server-0.1.11.dist-info/WHEEL
markitdown_mcp_server-0.1.11.dist-info/entry_points.txt
markitdown_mcp_server-0.1.11.dist-info/licenses/LICENSE
markitdown_mcp_server-0.1.11.dist-info/RECORD
