Metadata-Version: 2.4
Name: markitdown-mcp-server
Version: 0.1.11
Summary: MCP server for converting documents to markdown using MarkItDown
Project-URL: Homepage, https://github.com/yourusername/markitdown-mcp-server
Project-URL: Repository, https://github.com/yourusername/markitdown-mcp-server
Author-email: korigamik-hypr <korigamik@gmail.com>
License: MIT License
License-File: LICENSE
Keywords: document-conversion,markdown,mcp,server
Classifier: Development Status :: 3 - Alpha
Classifier: Intended Audience :: Developers
Classifier: Programming Language :: Python :: 3
Classifier: Programming Language :: Python :: 3.12
Requires-Python: >=3.12
Requires-Dist: markitdown>=0.1.1
Requires-Dist: mcp>=1.9.1
